pytailwind/__init__.py
pytailwind/__main__.py
pytailwind/classes.py
pytailwind/conversions.py
pytailwind/defaults.py
pytailwind/utils.py
pytailwind-0.0.7.dist-info/licenses/LICENSE.txt
pytailwind-0.0.7.dist-info/METADATA
pytailwind-0.0.7.dist-info/WHEEL
pytailwind-0.0.7.dist-info/entry_points.txt
pytailwind-0.0.7.dist-info/top_level.txt
pytailwind-0.0.7.dist-info/RECORD
