Metadata-Version: 2.4
Name: pytailwind
Version: 0.0.7
Summary: A tailwind parser written completely in python without js dependency (unofficial)
Home-page: https://github.com/shashstormer/pytailwindcss
Author: shashstormer
Author-email: shashstormer <shashanka5398@gmail.com>
License: MIT License
Project-URL: GitHub, https://github.com/shashstormer/pytailwindcss
Classifier: Development Status :: 4 - Beta
Classifier: Intended Audience :: Developers
Classifier: Programming Language :: Python :: 3.9
Classifier: Topic :: Software Development :: Libraries
License-File: LICENSE.txt
Requires-Dist: watchdog
Provides-Extra: watch
Requires-Dist: watchdog; extra == "watch"
Dynamic: author
Dynamic: home-page
Dynamic: license-file
